services/__init__.py
services/s3_service.py
s3_dog_food-0.0.8.dist-info/LICENSE
s3_dog_food-0.0.8.dist-info/METADATA
s3_dog_food-0.0.8.dist-info/WHEEL
s3_dog_food-0.0.8.dist-info/top_level.txt
s3_dog_food-0.0.8.dist-info/RECORD
