Metadata-Version: 2.1
Name: s3-dog-food
Version: 0.0.8
Summary: A small example package
Home-page: https://github.com/pypa/sampleproject
Author: rnachiappan, sbagavathy
Author-email: author@example.com
License: UNKNOWN
Platform: UNKNOWN
Classifier: Programming Language :: Python :: 3
Classifier: License :: OSI Approved :: MIT License
Classifier: Operating System :: OS Independent
Requires-Dist: boto3
Requires-Dist: botocore
